hbox/commands.py
hbox/config.py
hbox/logger.py
hbox/main.py
hbox/utils.py
hbox-0.3.5.dist-info/LICENSE
hbox-0.3.5.dist-info/METADATA
hbox-0.3.5.dist-info/WHEEL
hbox-0.3.5.dist-info/entry_points.txt
hbox-0.3.5.dist-info/RECORD
