Metadata-Version: 2.1
Name: hbox
Version: 0.3.5
Summary: CLI tool that leverages container technology to manage packages.
License: MIT
Author: Helton Carlos de Souza
Author-email: heltoncarlossouza@gmail.com
Requires-Python: >=3.12,<4.0
Classifier: License :: OSI Approved :: MIT License
Classifier: Programming Language :: Python :: 3
Classifier: Programming Language :: Python :: 3.12
Requires-Dist: pydantic (>=2.7.1,<3.0.0)
